pi_romulus/__init__.py
pi_romulus/romulus.py
pi_romulus-1.1.2.data/scripts/romulus.py
pi_romulus-1.1.2.dist-info/DESCRIPTION.rst
pi_romulus-1.1.2.dist-info/METADATA
pi_romulus-1.1.2.dist-info/RECORD
pi_romulus-1.1.2.dist-info/WHEEL
pi_romulus-1.1.2.dist-info/metadata.json
pi_romulus-1.1.2.dist-info/top_level.txt
